cas_gui/base.py
cas_gui/cameras/DCXCameraInterface.py
cas_gui/cameras/FileInterface.py
cas_gui/cameras/FleaCameraInterface.py
cas_gui/cameras/GenericCamera.py
cas_gui/cameras/KiraluxCamera.py
cas_gui/cameras/SimulatedCamera.py
cas_gui/cameras/WebCamera.py
cas_gui/cameras/WebCameraColour.py
cas_gui/res/Toggle_blue.png
cas_gui/res/Toggle_disable.png
cas_gui/res/Toggle_grey.png
cas_gui/res/cameras.csv
cas_gui/res/cas_modern.css
cas_gui/res/logo_256_red.png
cas_gui/res/resources.py
cas_gui/res/resources.qrc
cas_gui/res/__pycache__/resources.cpython-310.pyc
cas_gui/res/__pycache__/resources.cpython-311.pyc
cas_gui/res/icons/camera_white.svg
cas_gui/res/icons/chevron_white.svg
cas_gui/res/icons/copy_white.svg
cas_gui/res/icons/download_white.svg
cas_gui/res/icons/exit_white.svg
cas_gui/res/icons/eye_white.svg
cas_gui/res/icons/film_white.svg
cas_gui/res/icons/grid_white.svg
cas_gui/res/icons/play_white.svg
cas_gui/res/icons/save_white.svg
cas_gui/res/icons/settings_white.svg
cas_gui/res/icons/study_white.svg
cas_gui/subclasses/cas_bundle.py
cas_gui/threads/bundle_processor.py
cas_gui/threads/image_acquisition_thread.py
cas_gui/threads/image_processor_class.py
cas_gui/threads/image_processor_process.py
cas_gui/threads/image_processor_thread.py
cas_gui/utils/im_tools.py
cas_gui/widgets/double_slider.py
cas_gui/widgets/image_display.py
cas_gui/widgets/label_checkbox_widget.py
cas_gui/widgets/range_spin_box.py
cas_gui-1.0.4.dist-info/licenses/LICENSE
cas_gui-1.0.4.dist-info/METADATA
cas_gui-1.0.4.dist-info/WHEEL
cas_gui-1.0.4.dist-info/top_level.txt
cas_gui-1.0.4.dist-info/RECORD
