Metadata-Version: 2.4
Name: CAS-GUI
Version: 1.0.4
Summary: Python package for creating imaging system GUIs.
Author-email: Michael Hughes <m.r.hughes@kent.ac.uk>
License: MIT License
Project-URL: Homepage, https://github.com/MikeHughesKent/CAS/
Keywords: GUI,imaging,camera
Classifier: License :: OSI Approved :: MIT License
Classifier: Programming Language :: Python
Classifier: Programming Language :: Python :: 3
Requires-Python: >=3.10
License-File: LICENSE
Requires-Dist: matplotlib>=3.8
Requires-Dist: numpy>=1.26
Requires-Dist: opencv_python>=4.9
Requires-Dist: Pillow>=10.3
Requires-Dist: scipy>=1.13
Requires-Dist: pyqt5>=5.15
Requires-Dist: magicattr>=0.1.6
Dynamic: license-file
